Workbook
Name Slicer_Product_Category: #N/A
Name Slicer_Region: #N/A

Sheet Project_Blueprint
A1: Retail Sales Performance Analysis
A2: A retail company wants to understand its sales performance across regions, product categories, and time to improve profitability and operational decisions.
A4: Business Questions
A5: Which regions contribute the highest share of total sales and profit?
A6: Do regions with higher sales also maintain healthy profit margins?
A7: Which product categories are consistently underperforming in profitability?
A8: How do discount levels impact overall profit margins?
A9: Are there observable seasonal trends in sales performance?
A11: KPIs
A12: Total sales | C12: Sum of sales amount
A13: Total Profit | C13: Sum of (sales amount-cost)
A14: Profit Marin % | C14: Total profit / Total sales
A15: Average Discount % | C15: Average Discount applied per Order
A16: Sales per Order | C16: Total Sales / No of Orders
A17: Sales Contribution % by Region | C17: Region wise Revenue / Total Sales
A19: Data cleaning and preparation record
A20: Order dates are converted to short dates and month is extracted for seasonal patterns observation.
A21: Converted sales, cost and profit to numbers while discount is percentage for calculations.
A22: Region, City, Product_category, Product_name have no errors.
A23: No rows deleted.
A24: Added Columns- Month_name, Month_number, Profit_margin %, Sales_contribution %.

Sheet Raw_Data
A1: Order Date | B1: Region | C1: City | D1: Product Category | E1: Product Name | F1: Quantity Sold | G1: Sales Amount | H1: Cost | I1: Discount % | J1: Profit | K1: Month_name | L1: Month_Number | M1: Profit_margin % | N1: Sales_contribution %
A2: 45257 | B2: East | C2: Kolkata | D2: Clothing | E2: Jacket | F2: 5 | G2: 55974 | H2: 32968.61 | I2: 0.05 | J2: 23005.39 | K2: =TEXT(A2,"mmmm") -> November | L2: =MONTH(A2) -> 11 | M2: =J2/G2 -> 0.41100136 | N2: =G2/SUM(G:G) -> 0.00051834771
A3: 45220 | B3: East | C3: Kolkata | D3: Accessories | E3: Wallet | F3: 3 | G3: 5244 | H3: 4155.75 | I3: 0.2 | J3: 1088.25 | K3: =TEXT(A3,"mmmm") -> October | L3: =MONTH(A3) -> 10 | M3: =J3/G3 -> 0.20752288 | N3: =G3/SUM(G:G) -> 4.8562108e-05
A4: 44975 | B4: South | C4: Bangalore | D4: Electronics | E4: Headphones | F4: 2 | G4: 46708.8 | H4: 30733.75 | I4: 0.2 | J4: 15975.05 | K4: =TEXT(A4,"mmmm") -> February | L4: =MONTH(A4) -> 2 | M4: =J4/G4 -> 0.34201371 | N4: =G4/SUM(G:G) -> 0.00043254725
A5: 45170 | B5: East | C5: Bhubaneswar | D5: Clothing | E5: Jeans | F5: 4 | G5: 11689.2 | H5: 7546.73 | I5: 0.1 | J5: 4142.47 | K5: =TEXT(A5,"mmmm") -> September | L5: =MONTH(A5) -> 9 | M5: =J5/G5 -> 0.35438439 | N5: =G5/SUM(G:G) -> 0.00010824794
A6: 45200 | B6: West | C6: Mumbai | D6: Clothing | E6: T-Shirt | F6: 3 | G6: 101054.4 | H6: 66961.15 | I6: 0.2 | J6: 34093.25 | K6: =TEXT(A6,"mmmm") -> October | L6: =MONTH(A6) -> 10 | M6: =J6/G6 -> 0.33737522 | N6: =G6/SUM(G:G) -> 0.00093581515
A7: 45266 | B7: West | C7: Mumbai | D7: Accessories | E7: Bag | F7: 2 | G7: 87002 | H7: 48198.37 | I7: 0 | J7: 38803.63 | K7: =TEXT(A7,"mmmm") -> December | L7: =MONTH(A7) -> 12 | M7: =J7/G7 -> 0.44600848 | N7: =G7/SUM(G:G) -> 0.00080568278
A8: 44976 | B8: West | C8: Ahmedabad | D8: Accessories | E8: Belt | F8: 4 | G8: 63572.4 | H8: 49416.74 | I8: 0.1 | J8: 14155.66 | K8: =TEXT(A8,"mmmm") -> February | L8: =MONTH(A8) -> 2 | M8: =J8/G8 -> 0.2226699 | N8: =G8/SUM(G:G) -> 0.00058871276
A9: 45117 | B9: West | C9: Pune | D9: Furniture | E9: Table | F9: 6 | G9: 70976.7 | H9: 42317.27 | I9: 0.15 | J9: 28659.43 | K9: =TEXT(A9,"mmmm") -> July | L9: =MONTH(A9) -> 7 | M9: =J9/G9 -> 0.40378645 | N9: =G9/SUM(G:G) -> 0.00065728035
A10: 45230 | B10: South | C10: Chennai | D10: Accessories | E10: Bag | F10: 2 | G10: 45996.9 | H10: 32173.68 | I10: 0.15 | J10: 13823.22 | K10: =TEXT(A10,"mmmm") -> October | L10: =MONTH(A10) -> 10 | M10: =J10/G10 -> 0.30052504 | N10: =G10/SUM(G:G) -> 0.00042595469
A11: 45264 | B11: East | C11: Patna | D11: Clothing | E11: Shirt | F11: 1 | G11: 19802.4 | H11: 12815.51 | I11: 0.2 | J11: 6986.89 | K11: =TEXT(A11,"mmmm") -> December | L11: =MONTH(A11) -> 12 | M11: =J11/G11 -> 0.35283046 | N11: =G11/SUM(G:G) -> 0.0001833803
A12: 44967 | B12: East | C12: Kolkata | D12: Accessories | E12: Bag | F12: 1 | G12: 18481.55 | H12: 12672.32 | I12: 0.15 | J12: 5809.23 | K12: =TEXT(A12,"mmmm") -> February | L12: =MONTH(A12) -> 2 | M12: =J12/G12 -> 0.31432591 | N12: =G12/SUM(G:G) -> 0.00017114855
A13: 45062 | B13: North | C13: Jaipur | D13: Electronics | E13: Laptop | F13: 1 | G13: 41274 | H13: 30669.11 | I13: 0 | J13: 10604.89 | K13: =TEXT(A13,"mmmm") -> May | L13: =MONTH(A13) -> 5 | M13: =J13/G13 -> 0.25693875 | N13: =G13/SUM(G:G) -> 0.00038221824
... A1201: 44980 | B1201: East | C1201: Kolkata | D1201: Furniture | E1201: Cupboard | F1201: 4 | G1201: 60713.8 | H1201: 48512.81 | I1201: 0.15 | J1201: 12200.99 | K1201: =TEXT(A1201,"mmmm") -> February | L1201: =MONTH(A1201) -> 2 | M1201: =J1201/G1201 -> 0.20095909 | N1201: =G1201/SUM(G:G) -> 0.00056224067

Sheet Pivot_calculations
A2: Sum of Sales Amount | B2: Sum of Cost | C2: Sum of Profit | D2: Sum of Profit_Margin_% | E2: Sum of Quantity | G2: Disount % | H2: Average of Profit_margin % | J2: Month_number | K2: Sum of Sales Amount | M2: Disount % | N2: Sum of Sales Amount
A3: 1.0798543e+08 | B3: 73245434 | C3: 34739995 | D3: 0.32171003 | E3: 4753 | G3: 0 | H3: 0.32619241 | J3: 1 | K3: 7895798.2 | M3: 0 | N3: 22167111
G4: 0.05 | H4: 0.3280632 | J4: 2 | K4: 7550652.2 | M4: 0.05 | N4: 23809280
A5: Region | B5: Sum of Sales Amount | D5: Product_category | E5: Sum of Sales Amount | G5: 0.1 | H5: 0.31247247 | J5: 3 | K5: 9974091 | M5: 0.1 | N5: 23366604
A6: East | B6: 28558984 | D6: Accessories | E6: 25904378 | G6: 0.15 | H6: 0.31813021 | J6: 4 | K6: 6895182.9 | M6: 0.15 | N6: 20430605
A7: North | B7: 27595443 | D7: Clothing | E7: 26542346 | G7: 0.2 | H7: 0.33054814 | J7: 5 | K7: 7926196.9 | M7: 0.2 | N7: 18211829
A8: South | B8: 26767584 | D8: Electronics | E8: 29452171 | G8: Grand Total | H8: 0.32297085 | J8: 6 | K8: 10647209 | M8: Grand Total | N8: 1.0798543e+08
A9: West | B9: 25063418 | D9: Furniture | E9: 26086533 | J9: 7 | K9: 10129543
A10: Grand Total | B10: 1.0798543e+08 | D10: Grand Total | E10: 1.0798543e+08 | J10: 8 | K10: 11254863
J11: 9 | K11: 6814181.4
J12: 10 | K12: 9561441
A13: Sum of Sales Amount | B13: Product_category | H13: Region | I13: Sum of Sales Amount | J13: 11 | K13: 10909981
A14: Region | B14: Accessories | C14: Clothing | D14: Electronics | E14: Furniture | F14: Grand Total | H14: East | I14: 28558984 | J14: 12 | K14: 8426288.9
A15: East | B15: 5717675.5 | C15: 6515583.5 | D15: 8044987.5 | E15: 8280737.2 | F15: 28558984 | H15: North | I15: 27595443 | J15: Grand Total | K15: 1.0798543e+08
A16: North | B16: 6953636.3 | C16: 5451286.4 | D16: 8727111.2 | E16: 6463408.8 | F16: 27595443 | H16: South | I16: 26767584
A17: South | B17: 6401004.5 | C17: 7383624 | D17: 7047989 | E17: 5934967 | F17: 26767584 | H17: West | I17: 25063418
A18: West | B18: 6832062.3 | C18: 7191852.3 | D18: 5632083.3 | E18: 5407420.1 | F18: 25063418 | H18: Grand Total | I18: 1.0798543e+08 | K18: =AVERAGE(I14:I17) -> 26996357
A19: Grand Total | B19: 25904378 | C19: 26542346 | D19: 29452171 | E19: 26086533 | F19: 1.0798543e+08
A27: West's underperformance is primarily volume-driven, as profit magrings are comparble to other regions but total quantities sold are lower,indicating to weaker demand rather than pricing inefficiencies.
A28: Accessories are non Core products hence, their have low volume sales and low revenue. Suggesting there are supporting products and not the core revenue drivers.
A29: Higher discounting does not result in higher purchase volume, suggesting price inelastic demand for products. Hence, aggressive discounting may erase profit and may slow down growth.
A30: Sales uplift in Q3 shows potential demand due to large volumes rather than high pricing and seasonal demand pattern that can be leveraged.
A32: Count of Order Date
A33: 1200

Sheet Dashboard
A1: Sales & Profitability Performance Dashboard
A6: Total Sales | M6: Average Sales(Region) | R6: (Best) East Sales
A7: =GETPIVOTDATA("Sum of Sales Amount",Pivot_calculations!$A$2) -> 1.0798543e+08 | M7: =Pivot_calculations!K18 -> 26996357 | R7: =GETPIVOTDATA("Sum of Sales Amount",Pivot_calculations!A5,"Region",Pivot_calculations!A6) -> 28558984
G8: Profit Margin %
G9: =A12/A7 -> 0.32171003
A11: Total Profit | M11: Average Order Value | R11: (Worst) West Sales
A12: =GETPIVOTDATA("Sum of Profit",Pivot_calculations!$A$2) -> 34739995 | M12: =A7/GETPIVOTDATA("Order Date",Pivot_calculations!$A$32) -> 89987.857 | R12: =GETPIVOTDATA("Sum of Sales Amount",Pivot_calculations!A5,"Region",Pivot_calculations!A9) -> 25063418

Sheet Insights
A1: Key Insights
A2: Regionally, profit remains stable, But West region underperforms in both Sales and Profit.
A3: West-Furniture has weak performance with just 54.07 lakh Total sales. Since, furniture's average sale is 65.21 lakh and in west its less than that, its due to low demand
A4: Accessories contribute lowest to Total sales and Profit but has decent Profit margin (32.00%),suggesting less demand even after correct pricing.
A5: Profit Margins remain relatively stable across discount %. However, sales falls from 2.38Cr to 1.82Cr as discount increases from 5% to 20%. Suggesting diminishing returns from aggressive discounting
A6: Q3(July-Sept) has seasonal Uplift. Since, Average sales (9.89) and Profit (9.64) increases from Overall average of 8.33 (sales) and 8.33 (profit). Suggesting potential demand that can be leveraged by inventory and marketing planning.
A8: Root Cause Hypotheses
A9: West's underperformance is primarily volume-driven, as profit magrings are comparble to other regions but total quantities sold are lower,indicating to weaker demand rather than pricing inefficiencies.
A10: Accessories functions as a supporting category based on volume contribution. Hence,it has low volume sales and revenue. Suggesting that supporting products do not drive core revenue.
A11: Higher discounts does not drive higher purchase volume, suggesting price inelastic demand for products. Hence, aggressive discounting may erase profit and may slow down growth.
A12: Sales uplift in Q3 shows potential demand due to large volumes rather than high pricing and seasonal demand pattern that can be leveraged.
A14: Recommendations
... A22: Second, discounting beyond 5% fails to stimulate demand and instead reduces sales, indicating that performance is volume-driven rather than influenced by pricing or cost inefficiencies.
